{
    "filename": "zlgZF7a_jpeg.rf.14aa020af91fc3a1ef6d1259e61e0d83.jpg",
    "tesseract": {
        "raw_text": "",
        "fields": {
            "id_number": "",
            "date_of_birth_en": "",
            "issue_date_en": "",
            "expiry_date_en": "",
            "date_of_birth_th": "",
            "issue_date_th": "",
            "expiry_date_th": "",
            "name_english": "",
            "name_thai": ""
        },
        "time_seconds": 0.291
    },
    "easyocr": {
        "raw_text": "รุ์\n^",
        "fields": {
            "id_number": "",
            "date_of_birth_en": "",
            "issue_date_en": "",
            "expiry_date_en": "",
            "date_of_birth_th": "",
            "issue_date_th": "",
            "expiry_date_th": "",
            "name_english": "",
            "name_thai": ""
        },
        "time_seconds": 10.292
    }
}